main.py
setup.py
fadlearner.egg-info/PKG-INFO
fadlearner.egg-info/SOURCES.txt
fadlearner.egg-info/dependency_links.txt
fadlearner.egg-info/requires.txt
fadlearner.egg-info/top_level.txt