Metadata-Version: 2.1
Name: fadlearner
Version: 912.6
Summary: x
Author: x
Author-email: xxx@outlook.com
Requires-Dist: requests
